{"ticker":"KORDS","name":"KORDSA TEKNIK TEKSTIL","type":"Stock","industry":"TEKSTİL","mom":-0.298271,"fip":-0.068,"monthly":[{"month":"2025-02","momentum":-0.078684,"fip":-0.05,"neg_count":10,"pos_count":9,"flat_count":1,"total_days":20,"days":[{"date":"2025-02-03","ret":-0.038235},{"date":"2025-02-04","ret":0.004587},{"date":"2025-02-05","ret":-0.0122},{"date":"2025-02-06","ret":0.0116},{"date":"2025-02-07","ret":0.020564},{"date":"2025-02-10","ret":0.0},{"date":"2025-02-11","ret":-0.014925},{"date":"2025-02-12","ret":-0.013636},{"date":"2025-02-13","ret":0.000768},{"date":"2025-02-14","ret":-0.007675},{"date":"2025-02-17","ret":-0.013148},{"date":"2025-02-18","ret":0.009404},{"date":"2025-02-19","ret":-0.025621},{"date":"2025-02-20","ret":0.022311},{"date":"2025-02-21","ret":-0.014809},{"date":"2025-02-24","ret":0.0024},{"date":"2025-02-25","ret":-0.020521},{"date":"2025-02-26","ret":0.004},{"date":"2025-02-27","ret":0.008},{"date":"2025-02-28","ret":-0.002389}]},{"month":"2025-03","momentum":-0.090182,"fip":0.1,"neg_count":9,"pos_count":11,"flat_count":0,"total_days":20,"days":[{"date":"2025-03-03","ret":-0.036712},{"date":"2025-03-04","ret":-0.03894},{"date":"2025-03-05","ret":0.008621},{"date":"2025-03-06","ret":0.052137},{"date":"2025-03-07","ret":0.012998},{"date":"2025-03-10","ret":0.015237},{"date":"2025-03-11","ret":-0.004739},{"date":"2025-03-12","ret":0.0127},{"date":"2025-03-13","ret":0.011755},{"date":"2025-03-14","ret":0.000775},{"date":"2025-03-17","ret":0.000774},{"date":"2025-03-18","ret":-0.009281},{"date":"2025-03-19","ret":-0.086651},{"date":"2025-03-20","ret":-0.001709},{"date":"2025-03-21","ret":-0.068493},{"date":"2025-03-24","ret":0.005515},{"date":"2025-03-25","ret":0.035649},{"date":"2025-03-26","ret":-0.010591},{"date":"2025-03-27","ret":-0.005352},{"date":"2025-03-28","ret":0.022422}]},{"month":"2025-04","momentum":-0.066873,"fip":-0.2,"neg_count":12,"pos_count":8,"flat_count":0,"total_days":20,"days":[{"date":"2025-04-02","ret":-0.0088},{"date":"2025-04-03","ret":0.040708},{"date":"2025-04-04","ret":-0.0068},{"date":"2025-04-07","ret":0.0017},{"date":"2025-04-08","ret":0.0009},{"date":"2025-04-09","ret":0.0017},{"date":"2025-04-10","ret":0.001708},{"date":"2025-04-11","ret":-0.003309},{"date":"2025-04-14","ret":-0.00083},{"date":"2025-04-15","ret":-0.017442},{"date":"2025-04-16","ret":-0.033812},{"date":"2025-04-17","ret":-0.013123},{"date":"2025-04-18","ret":-0.012411},{"date":"2025-04-21","ret":0.005386},{"date":"2025-04-22","ret":0.066071},{"date":"2025-04-24","ret":-0.01675},{"date":"2025-04-25","ret":0.004259},{"date":"2025-04-28","ret":-0.027},{"date":"2025-04-29","ret":-0.0199},{"date":"2025-04-30","ret":-0.0265}]},{"month":"2025-05","momentum":-0.041541,"fip":-0.1,"neg_count":11,"pos_count":9,"flat_count":0,"total_days":20,"days":[{"date":"2025-05-02","ret":0.002727},{"date":"2025-05-05","ret":-0.004533},{"date":"2025-05-06","ret":0.0064},{"date":"2025-05-07","ret":-0.017195},{"date":"2025-05-08","ret":0.012891},{"date":"2025-05-09","ret":0.016364},{"date":"2025-05-12","ret":0.0295},{"date":"2025-05-13","ret":0.010426},{"date":"2025-05-14","ret":-0.0034},{"date":"2025-05-15","ret":-0.0198},{"date":"2025-05-16","ret":0.0352},{"date":"2025-05-20","ret":-0.002551},{"date":"2025-05-21","ret":-0.028986},{"date":"2025-05-22","ret":0.005268},{"date":"2025-05-23","ret":0.001747},{"date":"2025-05-26","ret":-0.01918},{"date":"2025-05-27","ret":-0.0178},{"date":"2025-05-28","ret":-0.017778},{"date":"2025-05-29","ret":-0.009955},{"date":"2025-05-30","ret":-0.0189}]},{"month":"2025-06","momentum":0.018291,"fip":-0.157895,"neg_count":8,"pos_count":11,"flat_count":0,"total_days":19,"days":[{"date":"2025-06-02","ret":-0.0201},{"date":"2025-06-03","ret":0.0224},{"date":"2025-06-04","ret":0.038391},{"date":"2025-06-05","ret":-0.007},{"date":"2025-06-10","ret":0.016844},{"date":"2025-06-11","ret":0.0061},{"date":"2025-06-12","ret":-0.0295},{"date":"2025-06-13","ret":-0.0393},{"date":"2025-06-16","ret":0.0102},{"date":"2025-06-17","ret":-0.0147},{"date":"2025-06-18","ret":-0.0205},{"date":"2025-06-19","ret":0.0124},{"date":"2025-06-20","ret":0.0085},{"date":"2025-06-23","ret":-0.0299},{"date":"2025-06-24","ret":0.0356},{"date":"2025-06-25","ret":-0.0112},{"date":"2025-06-26","ret":0.0009},{"date":"2025-06-27","ret":0.0038},{"date":"2025-06-30","ret":0.0402}]},{"month":"2025-07","momentum":0.106188,"fip":-0.272727,"neg_count":8,"pos_count":14,"flat_count":0,"total_days":22,"days":[{"date":"2025-07-01","ret":0.036},{"date":"2025-07-02","ret":-0.0104},{"date":"2025-07-03","ret":0.0123},{"date":"2025-07-04","ret":0.0139},{"date":"2025-07-07","ret":-0.0333},{"date":"2025-07-08","ret":-0.0195},{"date":"2025-07-09","ret":0.0171},{"date":"2025-07-10","ret":0.0115},{"date":"2025-07-11","ret":0.0035},{"date":"2025-07-14","ret":-0.0096},{"date":"2025-07-16","ret":-0.0159},{"date":"2025-07-17","ret":0.0224},{"date":"2025-07-18","ret":0.0009},{"date":"2025-07-21","ret":0.014},{"date":"2025-07-22","ret":-0.0043},{"date":"2025-07-23","ret":0.0564},{"date":"2025-07-24","ret":0.009},{"date":"2025-07-25","ret":-0.0212},{"date":"2025-07-28","ret":-0.0224},{"date":"2025-07-29","ret":0.0026},{"date":"2025-07-30","ret":0.011},{"date":"2025-07-31","ret":0.0319}]},{"month":"2025-08","momentum":0.12507,"fip":-0.142857,"neg_count":9,"pos_count":12,"flat_count":0,"total_days":21,"days":[{"date":"2025-08-01","ret":-0.0033},{"date":"2025-08-04","ret":0.0269},{"date":"2025-08-05","ret":-0.0056},{"date":"2025-08-06","ret":0.0176},{"date":"2025-08-07","ret":-0.0251},{"date":"2025-08-08","ret":-0.0097},{"date":"2025-08-11","ret":0.0033},{"date":"2025-08-12","ret":-0.0186},{"date":"2025-08-13","ret":0.0066},{"date":"2025-08-14","ret":0.007383},{"date":"2025-08-15","ret":0.016287},{"date":"2025-08-18","ret":0.039263},{"date":"2025-08-19","ret":-0.016962},{"date":"2025-08-20","ret":0.0102},{"date":"2025-08-21","ret":0.020186},{"date":"2025-08-22","ret":0.020186},{"date":"2025-08-25","ret":0.0181},{"date":"2025-08-26","ret":-0.0104},{"date":"2025-08-27","ret":0.0575},{"date":"2025-08-28","ret":-0.0219},{"date":"2025-08-29","ret":-0.009393}]},{"month":"2025-09","momentum":-0.080187,"fip":-0.272727,"neg_count":14,"pos_count":8,"flat_count":0,"total_days":22,"days":[{"date":"2025-09-01","ret":0.021152},{"date":"2025-09-02","ret":-0.026429},{"date":"2025-09-03","ret":-0.015407},{"date":"2025-09-04","ret":0.008197},{"date":"2025-09-05","ret":-0.014043},{"date":"2025-09-08","ret":-0.049475},{"date":"2025-09-09","ret":0.0221},{"date":"2025-09-10","ret":-0.013889},{"date":"2025-09-11","ret":-0.017997},{"date":"2025-09-12","ret":-0.004781},{"date":"2025-09-15","ret":-0.0392},{"date":"2025-09-16","ret":0.074167},{"date":"2025-09-17","ret":0.030256},{"date":"2025-09-18","ret":-0.029367},{"date":"2025-09-19","ret":0.013964},{"date":"2025-09-22","ret":-0.002295},{"date":"2025-09-23","ret":0.052147},{"date":"2025-09-24","ret":0.016035},{"date":"2025-09-25","ret":-0.009326},{"date":"2025-09-26","ret":-0.029689},{"date":"2025-09-29","ret":-0.027612},{"date":"2025-09-30","ret":-0.032233}]},{"month":"2025-10","momentum":-0.11182,"fip":-0.272727,"neg_count":14,"pos_count":8,"flat_count":0,"total_days":22,"days":[{"date":"2025-10-01","ret":0.0008},{"date":"2025-10-02","ret":-0.0571},{"date":"2025-10-03","ret":-0.015126},{"date":"2025-10-06","ret":-0.0179},{"date":"2025-10-07","ret":0.017376},{"date":"2025-10-08","ret":-0.017933},{"date":"2025-10-09","ret":-0.013913},{"date":"2025-10-10","ret":-0.000882},{"date":"2025-10-13","ret":-0.026478},{"date":"2025-10-14","ret":-0.029918},{"date":"2025-10-15","ret":0.018692},{"date":"2025-10-16","ret":-0.020183},{"date":"2025-10-17","ret":0.019663},{"date":"2025-10-20","ret":0.00551},{"date":"2025-10-21","ret":0.001826},{"date":"2025-10-22","ret":-0.0036},{"date":"2025-10-23","ret":-0.0046},{"date":"2025-10-24","ret":0.048713},{"date":"2025-10-27","ret":-0.007011},{"date":"2025-10-28","ret":-0.021183},{"date":"2025-10-30","ret":0.010821},{"date":"2025-10-31","ret":-0.000892}]},{"month":"2025-11","momentum":-0.121545,"fip":-0.45,"neg_count":14,"pos_count":5,"flat_count":1,"total_days":20,"days":[{"date":"2025-11-03","ret":0.002679},{"date":"2025-11-04","ret":-0.021371},{"date":"2025-11-05","ret":-0.0055},{"date":"2025-11-06","ret":0.0037},{"date":"2025-11-07","ret":-0.0201},{"date":"2025-11-10","ret":-0.0149},{"date":"2025-11-11","ret":-0.0217},{"date":"2025-11-12","ret":-0.0097},{"date":"2025-11-13","ret":-0.0068},{"date":"2025-11-14","ret":-0.005888},{"date":"2025-11-17","ret":0.0197},{"date":"2025-11-18","ret":-0.016457},{"date":"2025-11-19","ret":0.0108},{"date":"2025-11-20","ret":-0.012658},{"date":"2025-11-21","ret":-0.011834},{"date":"2025-11-24","ret":0.003},{"date":"2025-11-25","ret":-0.008159},{"date":"2025-11-26","ret":-0.008427},{"date":"2025-11-27","ret":0.0},{"date":"2025-11-28","ret":-0.004452}]},{"month":"2025-12","momentum":-0.007444,"fip":-0.130435,"neg_count":13,"pos_count":10,"flat_count":0,"total_days":23,"days":[{"date":"2025-12-01","ret":0.036585},{"date":"2025-12-02","ret":0.008824},{"date":"2025-12-03","ret":-0.0087},{"date":"2025-12-04","ret":-0.0216},{"date":"2025-12-05","ret":0.018036},{"date":"2025-12-08","ret":-0.003},{"date":"2025-12-09","ret":-0.001},{"date":"2025-12-10","ret":-0.0089},{"date":"2025-12-11","ret":0.002991},{"date":"2025-12-12","ret":0.022863},{"date":"2025-12-15","ret":0.0049},{"date":"2025-12-16","ret":-0.0155},{"date":"2025-12-17","ret":-0.0147},{"date":"2025-12-18","ret":0.003988},{"date":"2025-12-19","ret":-0.009335},{"date":"2025-12-22","ret":-0.01243},{"date":"2025-12-23","ret":-0.017052},{"date":"2025-12-24","ret":0.0264},{"date":"2025-12-25","ret":-0.0072},{"date":"2025-12-26","ret":-0.012971},{"date":"2025-12-29","ret":-0.012971},{"date":"2025-12-30","ret":0.0147},{"date":"2025-12-31","ret":0.0012}]},{"month":"2026-01","momentum":0.0369,"fip":0.0,"neg_count":10,"pos_count":10,"flat_count":1,"total_days":21,"days":[{"date":"2026-01-02","ret":0.0149},{"date":"2026-01-05","ret":-0.0045},{"date":"2026-01-06","ret":0.016194},{"date":"2026-01-07","ret":-0.0124},{"date":"2026-01-08","ret":-0.013312},{"date":"2026-01-09","ret":0.003271},{"date":"2026-01-12","ret":0.017115},{"date":"2026-01-13","ret":0.021635},{"date":"2026-01-14","ret":0.0},{"date":"2026-01-15","ret":0.016667},{"date":"2026-01-16","ret":-0.001929},{"date":"2026-01-19","ret":-0.0058},{"date":"2026-01-20","ret":-0.0068},{"date":"2026-01-21","ret":0.002},{"date":"2026-01-22","ret":0.0215},{"date":"2026-01-23","ret":0.011472},{"date":"2026-01-26","ret":0.0209},{"date":"2026-01-27","ret":-0.003714},{"date":"2026-01-28","ret":-0.027},{"date":"2026-01-29","ret":-0.018953},{"date":"2026-01-30","ret":-0.012879}]},{"month":"2026-02","momentum":-0.039183,"fip":-0.052632,"neg_count":10,"pos_count":9,"flat_count":0,"total_days":19,"days":[{"date":"2026-02-02","ret":0.008388},{"date":"2026-02-03","ret":0.003697},{"date":"2026-02-04","ret":0.012891},{"date":"2026-02-05","ret":-0.024545},{"date":"2026-02-06","ret":0.0019},{"date":"2026-02-09","ret":0.025116},{"date":"2026-02-10","ret":-0.001815},{"date":"2026-02-11","ret":-0.0055},{"date":"2026-02-12","ret":0.0411},{"date":"2026-02-13","ret":-0.007902},{"date":"2026-02-16","ret":0.020354},{"date":"2026-02-17","ret":-0.008673},{"date":"2026-02-18","ret":-0.029746},{"date":"2026-02-19","ret":-0.058611},{"date":"2026-02-20","ret":0.012452},{"date":"2026-02-23","ret":0.025544},{"date":"2026-02-24","ret":-0.017528},{"date":"2026-02-25","ret":-0.025352},{"date":"2026-02-26","ret":-0.006744}]}]}