{"ticker":"KRGYO","name":"KORFEZ GMYO","type":"Stock","industry":"GYO","mom":-0.40475,"fip":-0.04857,"monthly":[{"month":"2025-03","momentum":0.048896,"fip":-0.002445,"neg_count":9,"pos_count":10,"flat_count":1,"total_days":20,"is_partial":false,"days":[{"date":"2025-03-03","ret":-0.022222},{"date":"2025-03-04","ret":0.046364},{"date":"2025-03-05","ret":0.061685},{"date":"2025-03-06","ret":0.051555},{"date":"2025-03-07","ret":-0.028016},{"date":"2025-03-10","ret":0.020817},{"date":"2025-03-11","ret":-0.00549},{"date":"2025-03-12","ret":-0.0134},{"date":"2025-03-13","ret":0.011191},{"date":"2025-03-14","ret":-0.051383},{"date":"2025-03-17","ret":-0.031667},{"date":"2025-03-18","ret":-0.003442},{"date":"2025-03-19","ret":-0.067358},{"date":"2025-03-20","ret":0.087037},{"date":"2025-03-21","ret":-0.088586},{"date":"2025-03-24","ret":0.048598},{"date":"2025-03-25","ret":0.037433},{"date":"2025-03-26","ret":0.011168},{"date":"2025-03-27","ret":0.002549},{"date":"2025-03-28","ret":0.0}]},{"month":"2025-04","momentum":0.315808,"fip":-0.110533,"neg_count":6,"pos_count":13,"flat_count":1,"total_days":20,"is_partial":false,"days":[{"date":"2025-04-02","ret":0.0},{"date":"2025-04-03","ret":-0.012712},{"date":"2025-04-04","ret":0.0155},{"date":"2025-04-07","ret":0.0668},{"date":"2025-04-08","ret":-0.0507},{"date":"2025-04-09","ret":0.0434},{"date":"2025-04-10","ret":0.043406},{"date":"2025-04-11","ret":0.007937},{"date":"2025-04-14","ret":0.033858},{"date":"2025-04-15","ret":-0.054836},{"date":"2025-04-16","ret":-0.016922},{"date":"2025-04-17","ret":0.019672},{"date":"2025-04-18","ret":0.001608},{"date":"2025-04-21","ret":-0.012039},{"date":"2025-04-22","ret":0.011373},{"date":"2025-04-24","ret":0.082731},{"date":"2025-04-25","ret":0.043769},{"date":"2025-04-28","ret":0.0085},{"date":"2025-04-29","ret":0.0958},{"date":"2025-04-30","ret":-0.0354}]},{"month":"2025-05","momentum":-0.330107,"fip":-0.049516,"neg_count":11,"pos_count":8,"flat_count":1,"total_days":20,"is_partial":false,"days":[{"date":"2025-05-02","ret":0.029333},{"date":"2025-05-05","ret":0.009067},{"date":"2025-05-06","ret":-0.0308},{"date":"2025-05-07","ret":0.0},{"date":"2025-05-08","ret":-0.076159},{"date":"2025-05-09","ret":0.020789},{"date":"2025-05-12","ret":0.0154},{"date":"2025-05-13","ret":-0.024205},{"date":"2025-05-14","ret":-0.0078},{"date":"2025-05-15","ret":0.0114},{"date":"2025-05-16","ret":-0.0177},{"date":"2025-05-20","ret":-0.000719},{"date":"2025-05-21","ret":-0.023022},{"date":"2025-05-22","ret":0.030928},{"date":"2025-05-23","ret":0.030714},{"date":"2025-05-26","ret":0.060291},{"date":"2025-05-27","ret":-0.1},{"date":"2025-05-28","ret":-0.1},{"date":"2025-05-29","ret":-0.099492},{"date":"2025-05-30","ret":-0.0995}]},{"month":"2025-06","momentum":-0.304536,"fip":-0.016028,"neg_count":10,"pos_count":9,"flat_count":0,"total_days":19,"is_partial":false,"days":[{"date":"2025-06-02","ret":-0.0995},{"date":"2025-06-03","ret":-0.0807},{"date":"2025-06-04","ret":0.024038},{"date":"2025-06-05","ret":0.0012},{"date":"2025-06-10","ret":0.037515},{"date":"2025-06-11","ret":0.0158},{"date":"2025-06-12","ret":-0.0111},{"date":"2025-06-13","ret":0.0022},{"date":"2025-06-16","ret":-0.0123},{"date":"2025-06-17","ret":-0.008},{"date":"2025-06-18","ret":-0.0103},{"date":"2025-06-19","ret":0.0058},{"date":"2025-06-20","ret":0.0012},{"date":"2025-06-23","ret":-0.1},{"date":"2025-06-24","ret":-0.0192},{"date":"2025-06-25","ret":0.0169},{"date":"2025-06-26","ret":-0.0999},{"date":"2025-06-27","ret":-0.0199},{"date":"2025-06-30","ret":0.0145}]},{"month":"2025-07","momentum":0.229373,"fip":-0.020852,"neg_count":10,"pos_count":12,"flat_count":0,"total_days":22,"is_partial":false,"days":[{"date":"2025-07-01","ret":0.0029},{"date":"2025-07-02","ret":0.0014},{"date":"2025-07-03","ret":-0.0014},{"date":"2025-07-04","ret":-0.0728},{"date":"2025-07-07","ret":0.0077},{"date":"2025-07-08","ret":-0.0061},{"date":"2025-07-09","ret":-0.0046},{"date":"2025-07-10","ret":0.0031},{"date":"2025-07-11","ret":-0.0062},{"date":"2025-07-14","ret":0.0279},{"date":"2025-07-16","ret":-0.0361},{"date":"2025-07-17","ret":0.0625},{"date":"2025-07-18","ret":0.1},{"date":"2025-07-21","ret":0.0455},{"date":"2025-07-22","ret":0.0997},{"date":"2025-07-23","ret":0.0981},{"date":"2025-07-24","ret":0.0979},{"date":"2025-07-25","ret":-0.0986},{"date":"2025-07-28","ret":-0.0156},{"date":"2025-07-29","ret":-0.0317},{"date":"2025-07-30","ret":-0.0464},{"date":"2025-07-31","ret":0.0115}]},{"month":"2025-08","momentum":-0.052244,"fip":-0.019902,"neg_count":14,"pos_count":6,"flat_count":1,"total_days":21,"is_partial":false,"days":[{"date":"2025-08-01","ret":-0.0283},{"date":"2025-08-04","ret":0.0991},{"date":"2025-08-05","ret":0.0},{"date":"2025-08-06","ret":-0.0477},{"date":"2025-08-07","ret":0.0864},{"date":"2025-08-08","ret":-0.0615},{"date":"2025-08-11","ret":0.0191},{"date":"2025-08-12","ret":-0.008},{"date":"2025-08-13","ret":-0.0189},{"date":"2025-08-14","ret":-0.033058},{"date":"2025-08-15","ret":0.014245},{"date":"2025-08-18","ret":-0.002809},{"date":"2025-08-19","ret":-0.022535},{"date":"2025-08-20","ret":0.0173},{"date":"2025-08-21","ret":-0.005666},{"date":"2025-08-22","ret":-0.005666},{"date":"2025-08-25","ret":0.0388},{"date":"2025-08-26","ret":-0.0267},{"date":"2025-08-27","ret":-0.0247},{"date":"2025-08-28","ret":-0.0056},{"date":"2025-08-29","ret":-0.022599}]},{"month":"2025-09","momentum":-0.060686,"fip":-0.016551,"neg_count":13,"pos_count":7,"flat_count":2,"total_days":22,"is_partial":false,"days":[{"date":"2025-09-01","ret":0.017341},{"date":"2025-09-02","ret":-0.028409},{"date":"2025-09-03","ret":-0.002924},{"date":"2025-09-04","ret":0.038123},{"date":"2025-09-05","ret":-0.022599},{"date":"2025-09-08","ret":-0.034682},{"date":"2025-09-09","ret":0.0},{"date":"2025-09-10","ret":-0.005988},{"date":"2025-09-11","ret":-0.021084},{"date":"2025-09-12","ret":-0.024615},{"date":"2025-09-15","ret":0.0631},{"date":"2025-09-16","ret":0.023739},{"date":"2025-09-17","ret":-0.008696},{"date":"2025-09-18","ret":0.017544},{"date":"2025-09-19","ret":0.011494},{"date":"2025-09-22","ret":-0.008523},{"date":"2025-09-23","ret":-0.031519},{"date":"2025-09-24","ret":-0.014793},{"date":"2025-09-25","ret":-0.018018},{"date":"2025-09-26","ret":-0.021407},{"date":"2025-09-29","ret":0.0},{"date":"2025-09-30","ret":0.015625}]},{"month":"2025-10","momentum":0.018435,"fip":0.003352,"neg_count":12,"pos_count":8,"flat_count":2,"total_days":22,"is_partial":false,"days":[{"date":"2025-10-01","ret":-0.0031},{"date":"2025-10-02","ret":-0.0093},{"date":"2025-10-03","ret":0.015576},{"date":"2025-10-06","ret":-0.0153},{"date":"2025-10-07","ret":-0.009346},{"date":"2025-10-08","ret":0.0},{"date":"2025-10-09","ret":-0.006289},{"date":"2025-10-10","ret":0.0},{"date":"2025-10-13","ret":-0.022152},{"date":"2025-10-14","ret":-0.038835},{"date":"2025-10-15","ret":0.023569},{"date":"2025-10-16","ret":-0.016447},{"date":"2025-10-17","ret":-0.023411},{"date":"2025-10-20","ret":0.006849},{"date":"2025-10-21","ret":-0.006803},{"date":"2025-10-22","ret":0.0993},{"date":"2025-10-23","ret":-0.0436},{"date":"2025-10-24","ret":0.032573},{"date":"2025-10-27","ret":0.006309},{"date":"2025-10-28","ret":-0.009404},{"date":"2025-10-30","ret":0.006329},{"date":"2025-10-31","ret":0.040881}]},{"month":"2025-11","momentum":-0.048223,"fip":-0.007233,"neg_count":11,"pos_count":8,"flat_count":1,"total_days":20,"is_partial":false,"days":[{"date":"2025-11-03","ret":0.009063},{"date":"2025-11-04","ret":0.020958},{"date":"2025-11-05","ret":-0.0029},{"date":"2025-11-06","ret":0.0118},{"date":"2025-11-07","ret":-0.0029},{"date":"2025-11-10","ret":0.0},{"date":"2025-11-11","ret":-0.0262},{"date":"2025-11-12","ret":-0.015},{"date":"2025-11-13","ret":-0.0122},{"date":"2025-11-14","ret":-0.012308},{"date":"2025-11-17","ret":0.0156},{"date":"2025-11-18","ret":-0.003067},{"date":"2025-11-19","ret":0.0154},{"date":"2025-11-20","ret":0.024242},{"date":"2025-11-21","ret":0.011834},{"date":"2025-11-24","ret":-0.0292},{"date":"2025-11-25","ret":-0.027108},{"date":"2025-11-26","ret":-0.024768},{"date":"2025-11-27","ret":-0.006349},{"date":"2025-11-28","ret":0.00639}]},{"month":"2025-12","momentum":-0.066466,"fip":-0.020229,"neg_count":13,"pos_count":6,"flat_count":4,"total_days":23,"is_partial":false,"days":[{"date":"2025-12-01","ret":0.009524},{"date":"2025-12-02","ret":-0.009434},{"date":"2025-12-03","ret":-0.0159},{"date":"2025-12-04","ret":-0.0129},{"date":"2025-12-05","ret":-0.006536},{"date":"2025-12-08","ret":0.0066},{"date":"2025-12-09","ret":-0.0065},{"date":"2025-12-10","ret":-0.0066},{"date":"2025-12-11","ret":0.009934},{"date":"2025-12-12","ret":-0.003279},{"date":"2025-12-15","ret":0.0033},{"date":"2025-12-16","ret":0.0098},{"date":"2025-12-17","ret":-0.013},{"date":"2025-12-18","ret":-0.006579},{"date":"2025-12-19","ret":-0.006623},{"date":"2025-12-22","ret":-0.016667},{"date":"2025-12-23","ret":0.0},{"date":"2025-12-24","ret":-0.0068},{"date":"2025-12-25","ret":-0.0034},{"date":"2025-12-26","ret":0.0},{"date":"2025-12-29","ret":0.0},{"date":"2025-12-30","ret":0.0071},{"date":"2025-12-31","ret":0.0}]},{"month":"2026-01","momentum":-0.002716,"fip":-0.000517,"neg_count":12,"pos_count":8,"flat_count":1,"total_days":21,"is_partial":false,"days":[{"date":"2026-01-02","ret":0.0211},{"date":"2026-01-05","ret":-0.0034},{"date":"2026-01-06","ret":0.065517},{"date":"2026-01-07","ret":-0.0421},{"date":"2026-01-08","ret":-0.006757},{"date":"2026-01-09","ret":0.02381},{"date":"2026-01-12","ret":-0.006645},{"date":"2026-01-13","ret":0.010033},{"date":"2026-01-14","ret":-0.0232},{"date":"2026-01-15","ret":0.010169},{"date":"2026-01-16","ret":0.010067},{"date":"2026-01-19","ret":-0.01},{"date":"2026-01-20","ret":-0.0198},{"date":"2026-01-21","ret":-0.0034},{"date":"2026-01-22","ret":0.0101},{"date":"2026-01-23","ret":0.006689},{"date":"2026-01-26","ret":-0.01},{"date":"2026-01-27","ret":-0.006734},{"date":"2026-01-28","ret":-0.0203},{"date":"2026-01-29","ret":0.0},{"date":"2026-01-30","ret":-0.003311}]},{"month":"2026-02","momentum":-0.062685,"fip":-0.012537,"neg_count":12,"pos_count":8,"flat_count":0,"total_days":20,"is_partial":false,"days":[{"date":"2026-02-02","ret":-0.003322},{"date":"2026-02-03","ret":0.036667},{"date":"2026-02-04","ret":0.016077},{"date":"2026-02-05","ret":-0.012658},{"date":"2026-02-06","ret":-0.0096},{"date":"2026-02-09","ret":0.012945},{"date":"2026-02-10","ret":0.015974},{"date":"2026-02-11","ret":-0.0189},{"date":"2026-02-12","ret":-0.0093},{"date":"2026-02-13","ret":-0.006231},{"date":"2026-02-16","ret":0.015674},{"date":"2026-02-17","ret":0.012346},{"date":"2026-02-18","ret":-0.009146},{"date":"2026-02-19","ret":-0.046154},{"date":"2026-02-20","ret":0.022581},{"date":"2026-02-23","ret":0.003155},{"date":"2026-02-24","ret":-0.025157},{"date":"2026-02-25","ret":-0.035484},{"date":"2026-02-26","ret":-0.003344},{"date":"2026-02-27","ret":-0.016779}]},{"month":"2026-03","momentum":-0.030717,"fip":0.010239,"neg_count":1,"pos_count":3,"flat_count":2,"total_days":6,"is_partial":true,"days":[{"date":"2026-03-02","ret":-0.064846},{"date":"2026-03-03","ret":0.0},{"date":"2026-03-04","ret":0.0},{"date":"2026-03-05","ret":0.018248},{"date":"2026-03-06","ret":0.007168},{"date":"2026-03-09","ret":0.010676}]}]}