{"ticker":"YUNSA","name":"YUNSA YUNLU","type":"Stock","industry":"TEKSTİL","mom":0.424367,"fip":0.096,"monthly":[{"month":"2025-02","momentum":-0.126538,"fip":-0.45,"neg_count":13,"pos_count":4,"flat_count":3,"total_days":20,"days":[{"date":"2025-02-03","ret":-0.019704},{"date":"2025-02-04","ret":0.0},{"date":"2025-02-05","ret":-0.0168},{"date":"2025-02-06","ret":0.0102},{"date":"2025-02-07","ret":0.013491},{"date":"2025-02-10","ret":-0.004992},{"date":"2025-02-11","ret":0.0},{"date":"2025-02-12","ret":-0.016722},{"date":"2025-02-13","ret":0.0},{"date":"2025-02-14","ret":-0.008503},{"date":"2025-02-17","ret":-0.003431},{"date":"2025-02-18","ret":-0.015491},{"date":"2025-02-19","ret":-0.02972},{"date":"2025-02-20","ret":0.012613},{"date":"2025-02-21","ret":-0.023132},{"date":"2025-02-24","ret":-0.0036},{"date":"2025-02-25","ret":-0.027422},{"date":"2025-02-26","ret":-0.0038},{"date":"2025-02-27","ret":0.0075},{"date":"2025-02-28","ret":-0.003745}]},{"month":"2025-03","momentum":0.1353,"fip":-0.2,"neg_count":8,"pos_count":12,"flat_count":0,"total_days":20,"days":[{"date":"2025-03-03","ret":0.005639},{"date":"2025-03-04","ret":-0.018692},{"date":"2025-03-05","ret":0.022857},{"date":"2025-03-06","ret":0.039106},{"date":"2025-03-07","ret":0.023297},{"date":"2025-03-10","ret":0.005254},{"date":"2025-03-11","ret":-0.026132},{"date":"2025-03-12","ret":-0.0054},{"date":"2025-03-13","ret":0.02518},{"date":"2025-03-14","ret":0.014035},{"date":"2025-03-17","ret":0.053633},{"date":"2025-03-18","ret":0.098522},{"date":"2025-03-19","ret":-0.098655},{"date":"2025-03-20","ret":0.066335},{"date":"2025-03-21","ret":-0.080871},{"date":"2025-03-24","ret":-0.01692},{"date":"2025-03-25","ret":0.034423},{"date":"2025-03-26","ret":-0.019967},{"date":"2025-03-27","ret":-0.01528},{"date":"2025-03-28","ret":0.041379}]},{"month":"2025-04","momentum":-0.088543,"fip":-0.25,"neg_count":12,"pos_count":7,"flat_count":1,"total_days":20,"days":[{"date":"2025-04-02","ret":0.0116},{"date":"2025-04-03","ret":-0.001637},{"date":"2025-04-04","ret":-0.0131},{"date":"2025-04-07","ret":0.0},{"date":"2025-04-08","ret":0.015},{"date":"2025-04-09","ret":-0.0164},{"date":"2025-04-10","ret":-0.016367},{"date":"2025-04-11","ret":-0.004992},{"date":"2025-04-14","ret":0.001672},{"date":"2025-04-15","ret":-0.005008},{"date":"2025-04-16","ret":-0.016779},{"date":"2025-04-17","ret":0.018771},{"date":"2025-04-18","ret":-0.025126},{"date":"2025-04-21","ret":-0.012027},{"date":"2025-04-22","ret":-0.022609},{"date":"2025-04-24","ret":0.02669},{"date":"2025-04-25","ret":0.003466},{"date":"2025-04-28","ret":-0.0038},{"date":"2025-04-29","ret":-0.0332},{"date":"2025-04-30","ret":0.0036}]},{"month":"2025-05","momentum":-0.105267,"fip":-0.5,"neg_count":14,"pos_count":4,"flat_count":2,"total_days":20,"days":[{"date":"2025-05-02","ret":0.007194},{"date":"2025-05-05","ret":-0.014286},{"date":"2025-05-06","ret":-0.0018},{"date":"2025-05-07","ret":-0.027223},{"date":"2025-05-08","ret":0.024254},{"date":"2025-05-09","ret":-0.007286},{"date":"2025-05-12","ret":0.0239},{"date":"2025-05-13","ret":-0.010753},{"date":"2025-05-14","ret":0.0},{"date":"2025-05-15","ret":-0.0127},{"date":"2025-05-16","ret":0.0092},{"date":"2025-05-20","ret":-0.012727},{"date":"2025-05-21","ret":-0.014733},{"date":"2025-05-22","ret":0.0},{"date":"2025-05-23","ret":-0.003738},{"date":"2025-05-26","ret":-0.007505},{"date":"2025-05-27","ret":-0.0208},{"date":"2025-05-28","ret":-0.020794},{"date":"2025-05-29","ret":-0.011583},{"date":"2025-05-30","ret":-0.0078}]},{"month":"2025-06","momentum":0.009946,"fip":-0.052632,"neg_count":9,"pos_count":10,"flat_count":0,"total_days":19,"days":[{"date":"2025-06-02","ret":-0.0138},{"date":"2025-06-03","ret":0.012},{"date":"2025-06-04","ret":0.041502},{"date":"2025-06-05","ret":-0.0076},{"date":"2025-06-10","ret":0.007648},{"date":"2025-06-11","ret":0.0038},{"date":"2025-06-12","ret":-0.0321},{"date":"2025-06-13","ret":-0.0234},{"date":"2025-06-16","ret":0.002},{"date":"2025-06-17","ret":-0.006},{"date":"2025-06-18","ret":-0.0261},{"date":"2025-06-19","ret":-0.0124},{"date":"2025-06-20","ret":0.0313},{"date":"2025-06-23","ret":0.0182},{"date":"2025-06-24","ret":0.0219},{"date":"2025-06-25","ret":0.0078},{"date":"2025-06-26","ret":-0.0193},{"date":"2025-06-27","ret":-0.0138},{"date":"2025-06-30","ret":0.022}]},{"month":"2025-07","momentum":0.191132,"fip":-0.318182,"neg_count":7,"pos_count":14,"flat_count":1,"total_days":22,"days":[{"date":"2025-07-01","ret":0.0156},{"date":"2025-07-02","ret":0.0058},{"date":"2025-07-03","ret":0.0057},{"date":"2025-07-04","ret":0.0057},{"date":"2025-07-07","ret":-0.0151},{"date":"2025-07-08","ret":-0.0211},{"date":"2025-07-09","ret":0.0235},{"date":"2025-07-10","ret":0.0268},{"date":"2025-07-11","ret":-0.0019},{"date":"2025-07-14","ret":0.0056},{"date":"2025-07-16","ret":-0.0223},{"date":"2025-07-17","ret":0.0209},{"date":"2025-07-18","ret":0.0074},{"date":"2025-07-21","ret":0.0074},{"date":"2025-07-22","ret":0.0514},{"date":"2025-07-23","ret":-0.0192},{"date":"2025-07-24","ret":0.0569},{"date":"2025-07-25","ret":-0.0152},{"date":"2025-07-28","ret":-0.0154},{"date":"2025-07-29","ret":0.0347},{"date":"2025-07-30","ret":0.0235},{"date":"2025-07-31","ret":0.0}]},{"month":"2025-08","momentum":0.671561,"fip":-0.333333,"neg_count":7,"pos_count":14,"flat_count":0,"total_days":21,"days":[{"date":"2025-08-01","ret":0.0016},{"date":"2025-08-04","ret":0.0033},{"date":"2025-08-05","ret":0.0049},{"date":"2025-08-06","ret":0.0211},{"date":"2025-08-07","ret":-0.0191},{"date":"2025-08-08","ret":-0.0032},{"date":"2025-08-11","ret":0.0439},{"date":"2025-08-12","ret":-0.014},{"date":"2025-08-13","ret":-0.019},{"date":"2025-08-14","ret":0.00161},{"date":"2025-08-15","ret":-0.008039},{"date":"2025-08-18","ret":0.037277},{"date":"2025-08-19","ret":-0.01875},{"date":"2025-08-20","ret":0.0987},{"date":"2025-08-21","ret":0.1},{"date":"2025-08-22","ret":0.1},{"date":"2025-08-25","ret":0.0268},{"date":"2025-08-26","ret":-0.0301},{"date":"2025-08-27","ret":0.0997},{"date":"2025-08-28","ret":0.0147},{"date":"2025-08-29","ret":0.099034}]},{"month":"2025-09","momentum":-0.207693,"fip":-0.454545,"neg_count":16,"pos_count":6,"flat_count":0,"total_days":22,"days":[{"date":"2025-09-01","ret":-0.050549},{"date":"2025-09-02","ret":-0.039352},{"date":"2025-09-03","ret":-0.021687},{"date":"2025-09-04","ret":0.003695},{"date":"2025-09-05","ret":0.018405},{"date":"2025-09-08","ret":0.00241},{"date":"2025-09-09","ret":-0.0108},{"date":"2025-09-10","ret":-0.023086},{"date":"2025-09-11","ret":-0.041045},{"date":"2025-09-12","ret":-0.002594},{"date":"2025-09-15","ret":0.0637},{"date":"2025-09-16","ret":0.015892},{"date":"2025-09-17","ret":-0.012034},{"date":"2025-09-18","ret":-0.001218},{"date":"2025-09-19","ret":-0.003659},{"date":"2025-09-22","ret":-0.001224},{"date":"2025-09-23","ret":-0.028186},{"date":"2025-09-24","ret":0.002522},{"date":"2025-09-25","ret":-0.018868},{"date":"2025-09-26","ret":-0.023077},{"date":"2025-09-29","ret":-0.040682},{"date":"2025-09-30","ret":-0.01368}]},{"month":"2025-10","momentum":0.04719,"fip":0.090909,"neg_count":12,"pos_count":10,"flat_count":0,"total_days":22,"days":[{"date":"2025-10-01","ret":0.0153},{"date":"2025-10-02","ret":-0.0314},{"date":"2025-10-03","ret":-0.005642},{"date":"2025-10-06","ret":-0.0099},{"date":"2025-10-07","ret":0.014327},{"date":"2025-10-08","ret":-0.014124},{"date":"2025-10-09","ret":0.047278},{"date":"2025-10-10","ret":0.062927},{"date":"2025-10-13","ret":-0.018018},{"date":"2025-10-14","ret":0.039318},{"date":"2025-10-15","ret":-0.047919},{"date":"2025-10-16","ret":-0.049007},{"date":"2025-10-17","ret":-0.012535},{"date":"2025-10-20","ret":-0.00141},{"date":"2025-10-21","ret":0.029661},{"date":"2025-10-22","ret":-0.0055},{"date":"2025-10-23","ret":-0.0166},{"date":"2025-10-24","ret":0.035063},{"date":"2025-10-27","ret":-0.004065},{"date":"2025-10-28","ret":0.002721},{"date":"2025-10-30","ret":0.006784},{"date":"2025-10-31","ret":0.01752}]},{"month":"2025-11","momentum":0.104653,"fip":0.1,"neg_count":11,"pos_count":9,"flat_count":0,"total_days":20,"days":[{"date":"2025-11-03","ret":0.023841},{"date":"2025-11-04","ret":0.063389},{"date":"2025-11-05","ret":-0.0195},{"date":"2025-11-06","ret":0.0012},{"date":"2025-11-07","ret":0.0991},{"date":"2025-11-10","ret":0.0271},{"date":"2025-11-11","ret":-0.0406},{"date":"2025-11-12","ret":0.0183},{"date":"2025-11-13","ret":-0.0449},{"date":"2025-11-14","ret":0.001176},{"date":"2025-11-17","ret":0.0564},{"date":"2025-11-18","ret":-0.003337},{"date":"2025-11-19","ret":-0.01},{"date":"2025-11-20","ret":0.048478},{"date":"2025-11-21","ret":-0.031183},{"date":"2025-11-24","ret":-0.0433},{"date":"2025-11-25","ret":-0.00116},{"date":"2025-11-26","ret":-0.012776},{"date":"2025-11-27","ret":-0.008235},{"date":"2025-11-28","ret":-0.010676}]},{"month":"2025-12","momentum":-0.113485,"fip":-0.26087,"neg_count":14,"pos_count":8,"flat_count":1,"total_days":23,"days":[{"date":"2025-12-01","ret":0.031175},{"date":"2025-12-02","ret":-0.00814},{"date":"2025-12-03","ret":-0.0164},{"date":"2025-12-04","ret":-0.0095},{"date":"2025-12-05","ret":0.001203},{"date":"2025-12-08","ret":0.0012},{"date":"2025-12-09","ret":-0.0048},{"date":"2025-12-10","ret":-0.0229},{"date":"2025-12-11","ret":0.004944},{"date":"2025-12-12","ret":0.01722},{"date":"2025-12-15","ret":-0.0036},{"date":"2025-12-16","ret":-0.0049},{"date":"2025-12-17","ret":-0.0207},{"date":"2025-12-18","ret":0.002491},{"date":"2025-12-19","ret":0.003727},{"date":"2025-12-22","ret":-0.02599},{"date":"2025-12-23","ret":-0.013977},{"date":"2025-12-24","ret":-0.0064},{"date":"2025-12-25","ret":-0.0116},{"date":"2025-12-26","ret":-0.018277},{"date":"2025-12-29","ret":-0.018277},{"date":"2025-12-30","ret":0.0},{"date":"2025-12-31","ret":0.0053}]},{"month":"2026-01","momentum":0.078019,"fip":-0.047619,"neg_count":10,"pos_count":11,"flat_count":0,"total_days":21,"days":[{"date":"2026-01-02","ret":0.0106},{"date":"2026-01-05","ret":-0.0039},{"date":"2026-01-06","ret":0.010417},{"date":"2026-01-07","ret":-0.0271},{"date":"2026-01-08","ret":0.001325},{"date":"2026-01-09","ret":-0.002646},{"date":"2026-01-12","ret":0.027851},{"date":"2026-01-13","ret":0.050323},{"date":"2026-01-14","ret":-0.0258},{"date":"2026-01-15","ret":0.016393},{"date":"2026-01-16","ret":0.009926},{"date":"2026-01-19","ret":-0.0037},{"date":"2026-01-20","ret":-0.0136},{"date":"2026-01-21","ret":0.0012},{"date":"2026-01-22","ret":0.0559},{"date":"2026-01-23","ret":-0.001151},{"date":"2026-01-26","ret":0.0195},{"date":"2026-01-27","ret":0.001126},{"date":"2026-01-28","ret":-0.0067},{"date":"2026-01-29","ret":-0.020362},{"date":"2026-01-30","ret":-0.01963}]},{"month":"2026-02","momentum":0.006982,"fip":0.2,"neg_count":12,"pos_count":8,"flat_count":0,"total_days":20,"days":[{"date":"2026-02-02","ret":-0.001178},{"date":"2026-02-03","ret":0.040094},{"date":"2026-02-04","ret":0.049887},{"date":"2026-02-05","ret":0.015119},{"date":"2026-02-06","ret":-0.0234},{"date":"2026-02-09","ret":0.099129},{"date":"2026-02-10","ret":-0.000991},{"date":"2026-02-11","ret":-0.0268},{"date":"2026-02-12","ret":-0.0058},{"date":"2026-02-13","ret":-0.020408},{"date":"2026-02-16","ret":0.018849},{"date":"2026-02-17","ret":0.080818},{"date":"2026-02-18","ret":-0.1},{"date":"2026-02-19","ret":-0.071071},{"date":"2026-02-20","ret":0.015086},{"date":"2026-02-23","ret":-0.012739},{"date":"2026-02-24","ret":-0.004301},{"date":"2026-02-25","ret":-0.011879},{"date":"2026-02-26","ret":-0.017486},{"date":"2026-02-27","ret":0.003337}]}]}